app/__init__.py
app/config.py
app/application/__init__.py
app/application/services/__init__.py
app/application/services/contact.py
app/application/services/deal.py
app/domain/__init__.py
app/domain/bitrix_types.py
app/domain/entities/__init__.py
app/domain/entities/base_entity.py
app/domain/entities/contact.py
app/domain/entities/deal.py
app/domain/entities/smart_process.py
app/domain/interfaces/__init__.py
app/domain/interfaces/base_repository.py
app/infrastructure/__init__.py
app/infrastructure/ioc.py
app/infrastructure/bitrix/__init__.py
app/infrastructure/bitrix/bitrix_contact_repository.py
app/infrastructure/bitrix/bitrix_deal_repository.py
app/infrastructure/bitrix/repository_factory.py
app/infrastructure/bitrix/mixins/__init__.py
app/infrastructure/bitrix/mixins/batch_operations.py
app/infrastructure/bitrix/mixins/error_handling.py
app/infrastructure/bitrix/mixins/filter_builder.py
app/infrastructure/bitrix/mixins/pagination.py
app/infrastructure/bitrix/mixins/read.py
app/infrastructure/bitrix/mixins/relationship.py
app/infrastructure/bitrix/mixins/write.py
app/infrastructure/logging/__init__.py
app/infrastructure/logging/logger.py
app/infrastructure/mcp/server.py
app/infrastructure/mcp/handlers/__init__.py
app/infrastructure/mcp/handlers/contact.py
app/infrastructure/mcp/handlers/deal.py
app/presentation/mcp.py
mcp_server_b24-0.1.0.dist-info/METADATA
mcp_server_b24-0.1.0.dist-info/WHEEL
mcp_server_b24-0.1.0.dist-info/entry_points.txt
mcp_server_b24-0.1.0.dist-info/RECORD
