Metadata-Version: 2.4
Name: mcp-server-b24
Version: 0.1.0
Summary: Add your description here
Requires-Python: >=3.12
Requires-Dist: fast-bitrix24>=1.8.4
Requires-Dist: mcp[cli]>=1.4.1
Requires-Dist: pydantic-settings>=2.8.1
Requires-Dist: pydantic>=2.10.6
Requires-Dist: ruff>=0.11.0
Requires-Dist: structlog>=25.2.0
Requires-Dist: wireup>=0.16.0
